chenv/__init__.py
chenv/cli.py
chenv/console.py
chenv/fs.py
chenv/main.py
chenv/models/__init__.py
chenv/models/output.py
chenv/settings.py
chenv/subcommands/__init__.py
chenv/subcommands/blank/__init__.py
chenv/subcommands/blank/collector.py
chenv/subcommands/heroku/__init__.py
chenv/subcommands/heroku/collector.py
chenv/subcommands/local/__init__.py
chenv/subcommands/local/collector.py
chenv/subcommands/which/__init__.py
chenv/subcommands/which/which.py
chenv/transform.py
chenv-0.4.2.dist-info/entry_points.txt
chenv-0.4.2.dist-info/LICENSE
chenv-0.4.2.dist-info/WHEEL
chenv-0.4.2.dist-info/METADATA
chenv-0.4.2.dist-info/RECORD
