Metadata-Version: 2.1
Name: chenv
Version: 0.4.2
Summary: modern local environment management
Home-page: https://github.com/jonathan-shemer/chenv
License: MIT
Keywords: chenv,dotenv,enviroment
Author: Jonathan Shemer
Author-email: i@jonathanshemer.com
Requires-Python: >=3.8,<3.10
Classifier: License :: OSI Approved :: MIT License
Classifier: Programming Language :: Python :: 3
Classifier: Programming Language :: Python :: 3.8
Classifier: Programming Language :: Python :: 3.9
Requires-Dist: click (>=8.0.1,<9.0.0)
Requires-Dist: desert (>=2020.11.18,<2021.0.0)
Requires-Dist: httpx (>=0.19.0,<0.20.0)
Requires-Dist: marshmallow (>=3.13.0,<4.0.0)
Requires-Dist: python-dotenv (>=0.19.1,<0.20.0)
Requires-Dist: pytype (>=2021.10.18,<2022.0.0)
Requires-Dist: questionary (>=1.10.0,<2.0.0)
Requires-Dist: toolz (>=0.11.1,<0.12.0)
Project-URL: Documentation, https://chenv.readthedocs.io
Project-URL: Repository, https://github.com/jonathan-shemer/chenv
